PWTLoader/__init__.py
PWTLoader/loader.py
PWTLoader-0.2.4.dist-info/LICENSE
PWTLoader-0.2.4.dist-info/METADATA
PWTLoader-0.2.4.dist-info/WHEEL
PWTLoader-0.2.4.dist-info/top_level.txt
PWTLoader-0.2.4.dist-info/RECORD
