Metadata-Version: 2.1
Name: PWTLoader
Version: 0.2.4
Summary: A lightweigh loader for data from Penn World Table datasets via Dataverse
Home-page: https://github.com/Sarv1926/notjustmacro
Author: Sarvesh Ingle
Author-email: ingle.sarvesh1926@gmail.com
License: MIT
Keywords: pwt,penn world table,economics,data loader,econometrics
Classifier: Programming Language :: Python :: 3
Classifier: License :: OSI Approved :: MIT License
Requires-Python: >=3.7
License-File: LICENSE
Requires-Dist: pandas
Requires-Dist: beautifulsoup4
Requires-Dist: lxml
Requires-Dist: requests
Requires-Dist: html5lib
